DLSiteSpider/__init__.py
DLSiteSpider/dynamic.py
DLSiteSpider/static.py
DLSiteSpider/test_dynamic.py
DLSiteSpider/test_static.py
DLSiteSpider/utils.py
DLSiteSpider-0.1.2.dist-info/METADATA
DLSiteSpider-0.1.2.dist-info/WHEEL
DLSiteSpider-0.1.2.dist-info/top_level.txt
DLSiteSpider-0.1.2.dist-info/RECORD
